Metadata-Version: 1.0
Name: mdtui
Version: 0.0.2.post5
Summary: A TUI to search and download from the new MangaDex API v5
Home-page: https://git.geraldwu.com/gerald/mdtui
Author: 98WuG
Author-email: UNKNOWN
License: AGPL-3.0
Platform: UNKNOWN
